sort_my_files/__init__.py
sort_my_files/__main__.py
sort_my_files/main.py
sort_my_files-0.1.1.dist-info/entry_points.txt
sort_my_files-0.1.1.dist-info/WHEEL
sort_my_files-0.1.1.dist-info/METADATA
sort_my_files-0.1.1.dist-info/RECORD
