Metadata-Version: 2.1
Name: sort-my-files
Version: 0.1.1
Summary: 
Author: Daniel Evans
Author-email: me@daredoes.work
Requires-Python: >=3.9,<4.0
Classifier: Programming Language :: Python :: 3
Classifier: Programming Language :: Python :: 3.10
Classifier: Programming Language :: Python :: 3.9
Requires-Dist: typer (>=0.4.0,<0.5.0)
